mycalc/calculator.py
dodoria721-0.0.1.dist-info/METADATA
dodoria721-0.0.1.dist-info/WHEEL
dodoria721-0.0.1.dist-info/top_level.txt
dodoria721-0.0.1.dist-info/RECORD
