Metadata-Version: 2.1
Name: dodoria721
Version: 0.0.1
Summary: my calculator
Home-page: https://github.com/dodoria721/calc0001
Author: dowon
License: UNKNOWN
Platform: UNKNOWN
Classifier: Programming Language :: Python :: 3
